CHANGES.rst
MANIFEST.in
README.rst
setup.cfg
setup.py
collective/__init__.py
collective.notifications.egg-info/PKG-INFO
collective.notifications.egg-info/SOURCES.txt
collective.notifications.egg-info/dependency_links.txt
collective.notifications.egg-info/entry_points.txt
collective.notifications.egg-info/namespace_packages.txt
collective.notifications.egg-info/not-zip-safe
collective.notifications.egg-info/requires.txt
collective.notifications.egg-info/top_level.txt
collective/notifications/__init__.py
collective/notifications/configure.zcml
collective/notifications/exportimport.py
collective/notifications/external.py
collective/notifications/interfaces.py
collective/notifications/notifications.py
collective/notifications/pasync.py
collective/notifications/profiles.zcml
collective/notifications/tasks.py
collective/notifications/testing.py
collective/notifications/browser/__init__.py
collective/notifications/browser/configure.zcml
collective/notifications/browser/notifications.py
collective/notifications/browser/template_overrides/plone.app.layout.viewlets.toolbar.pt
collective/notifications/browser/templates/notifications.pt
collective/notifications/browser/templates/site_notifications.pt
collective/notifications/profiles/default/collective.notifications.txt
collective/notifications/profiles/default/controlpanel.xml
collective/notifications/profiles/default/metadata.xml
collective/notifications/profiles/uninstall/collective.notifications.uninstall.txt
collective/notifications/profiles/uninstall/controlpanel.xml
collective/notifications/profiles/uninstall/import_steps.xml
collective/notifications/tests/__init__.py
collective/notifications/tests/base.py
collective/notifications/tests/test_notifications.py
collective/notifications/upgrades/__init__.py
collective/notifications/upgrades/configure.zcml
collective/notifications/upgrades/to1002.py