Metadata-Version: 2.1
Name: collective.notifications
Version: 1.0
Summary: Provides notifications for users.
Home-page: http://svn.plone.org/svn/collective/
Author: enfold
Author-email: info@enfoldsystems.com
License: GPL
Keywords: Plone Notifications
Platform: UNKNOWN
Classifier: Framework :: Plone
Classifier: Framework :: Plone :: 5.0
Classifier: Framework :: Plone :: 5.1
Classifier: Framework :: Plone :: 5.2
Classifier: Programming Language :: Python
Classifier: Programming Language :: Python :: 2.7
Classifier: Programming Language :: Python :: 3.7
Classifier: Operating System :: OS Independent
Provides-Extra: celery
